fastermqtt/__init__.py
fastermqtt/broker.py
fastermqtt/dependencies.py
fastermqtt/exceptions.py
fastermqtt/middleware.py
fastermqtt/router.py
fastermqtt/serialization.py
fastermqtt/types.py
fastermqtt-0.1.0.dist-info/METADATA
fastermqtt-0.1.0.dist-info/WHEEL
fastermqtt-0.1.0.dist-info/licenses/LICENSE
fastermqtt-0.1.0.dist-info/RECORD
