Metadata-Version: 2.4
Name: fastermqtt
Version: 0.1.0
Summary: A FastAPI-style MQTT framework with dependency injection, topic path parameters, and hierarchical routing
Project-URL: Homepage, https://github.com/Foxerine/fastermqtt
Project-URL: Documentation, https://github.com/Foxerine/fastermqtt#readme
Project-URL: Repository, https://github.com/Foxerine/fastermqtt
Project-URL: Issues, https://github.com/Foxerine/fastermqtt/issues
Author-email: Foxerine <foxerine@users.noreply.github.com>
License-Expression: MIT
License-File: LICENSE
Keywords: async,fastapi,framework,iot,messaging,mqtt,pubsub
Classifier: Development Status :: 4 - Beta
Classifier: Framework :: FastAPI
Classifier: Intended Audience :: Developers
Classifier: License :: OSI Approved :: MIT License
Classifier: Operating System :: OS Independent
Classifier: Programming Language :: Python :: 3
Classifier: Programming Language :: Python :: 3.10
Classifier: Programming Language :: Python :: 3.11
Classifier: Programming Language :: Python :: 3.12
Classifier: Programming Language :: Python :: 3.13
Classifier: Topic :: Internet
Classifier: Topic :: Software Development :: Libraries :: Python Modules
Classifier: Typing :: Typed
Requires-Python: >=3.10
Requires-Dist: fastapi>=0.100.0
Requires-Dist: gmqtt>=0.6.0
Requires-Dist: orjson>=3.0.0
Requires-Dist: pydantic>=2.0.0
Provides-Extra: dev
Requires-Dist: pytest-asyncio>=0.21.0; extra == 'dev'
Requires-Dist: pytest>=7.0.0; extra == 'dev'
Requires-Dist: ruff>=0.1.0; extra == 'dev'
